mxy/__init__.py
mxy/mxy_test.py
mxy-1.0.dist-info/LICENSE
mxy-1.0.dist-info/METADATA
mxy-1.0.dist-info/WHEEL
mxy-1.0.dist-info/top_level.txt
mxy-1.0.dist-info/RECORD
