Metadata-Version: 2.1
Name: mxy
Version: 1.0
Summary: a test file
Author: xyMa
Author-email: xyMa00@126.com
Classifier: Programming Language :: Python :: 3
Classifier: License :: OSI Approved :: MIT License
Classifier: Operating System :: OS Independent
Requires-Python: >=3.7.0
License-File: LICENSE
Requires-Dist: pillow
